ztools/__init__.py
ztools/common/__init__.py
ztools/common/file.py
ztools/common/hash.py
ztools/common/sheet.py
ztools/db/CRUD.py
ztools/db/MySQL.py
ztools/db/SQLite.py
ztools/db/__init__.py
ztools/ds/__init__.py
ztools/ds/tbasic.py
ztools/ds/tqueue.py
ztools/ds/tstack.py
ztools/gui/__init__.py
ztools/gui/plot.py
ztools/utils/__init__.py
ztools/utils/progressbar.py
ztools/utils/timeout.py
ztools/utils/zemail.py
ztools/utils/zprint.py
ztools/ver/__init__.py
ztools/ver/zgit.py
ztools-2.4.7.dist-info/LICENSE
ztools-2.4.7.dist-info/METADATA
ztools-2.4.7.dist-info/WHEEL
ztools-2.4.7.dist-info/entry_points.txt
ztools-2.4.7.dist-info/top_level.txt
ztools-2.4.7.dist-info/zip-safe
ztools-2.4.7.dist-info/RECORD
