Metadata-Version: 2.1
Name: ztools
Version: 2.4.7
Summary: ToolBox for Python, Easy to Use.
Home-page: https://github.com/zoumingzhe/ztools
Author: Zou Mingzhe
Author-email: zoumingzhe@qq.com
License: MIT
Project-URL: Source Code, https://github.com/zoumingzhe/ztools
Project-URL: Bug Tracker, https://github.com/zoumingzhe/ztools/issues
Project-URL: Documentation, https://github.com/zoumingzhe/ztools
Keywords: ztools
Platform: any
Classifier: Programming Language :: Python
Classifier: Programming Language :: Python :: 3
Requires-Python: >=3.6
License-File: LICENSE
